README
setup.py
subargparse/__init__.py
subargparse.egg-info/PKG-INFO
subargparse.egg-info/SOURCES.txt
subargparse.egg-info/dependency_links.txt
subargparse.egg-info/requires.txt
subargparse.egg-info/top_level.txt