Metadata-Version: 1.1
Name: subargparse
Version: 1.1
Summary: A module for better handling sub-commands in argparse
Home-page: http://github.com/ykaridi/subargparse
Author: Yonatan Karidi Heller
Author-email: ykaridi@gmail.com
License: MIT
Download-URL: https://github.com/ykaridi/subargparse/archive/1.1.tar.gz
Keywords: subparser subcommand argparse
Platform: UNKNOWN
